kql/__init__.py
kql/stein.py
kql-1.2.12.dist-info/METADATA
kql-1.2.12.dist-info/WHEEL
kql-1.2.12.dist-info/top_level.txt
kql-1.2.12.dist-info/RECORD
