Metadata-Version: 2.4
Name: kql
Version: 1.2.12
Summary: A Python package for user info, username generation, Instagram checking, and email validation.
Home-page: https://github.com/yourusername/steinlurks
Author: STEIN
Author-email: devilsteinshorts@gmail.com
Classifier: Programming Language :: Python :: 3
Classifier: License :: OSI Approved :: MIT License
Classifier: Operating System :: OS Independent
Requires-Python: >=3.6
Requires-Dist: requests
Dynamic: author
Dynamic: author-email
Dynamic: classifier
Dynamic: description
Dynamic: description-content-type
Dynamic: home-page
Dynamic: requires-dist
Dynamic: requires-python
Dynamic: summary
